cryptoolzf/__init__.py
cryptoolzf/base.py
cryptoolzf/factory.py
cryptoolzf/printer.py
cryptoolzf/utils.py
cryptoolzf/app/__init__.py
cryptoolzf/app/cli/__init__.py
cryptoolzf/app/cli/__main__.py
cryptoolzf/app/cli/cryptoolzf.py
cryptoolzf/app/cli/keys.py
cryptoolzf/app/cli/primes.py
cryptoolzf/app/run/__init__.py
cryptoolzf/app/run/dummies.py
cryptoolzf/app/run/runner.py
cryptoolzf/app/tools/__init__.py
cryptoolzf/app/tools/base.py
cryptoolzf/app/tools/keys/__init__.py
cryptoolzf/app/tools/keys/base.py
cryptoolzf/app/tools/keys/keys.py
cryptoolzf/app/tools/keys/dropins/__init__.py
cryptoolzf/app/tools/keys/dropins/eth.py
cryptoolzf/crypto/__init__.py
cryptoolzf/crypto/circuits.py
cryptoolzf/crypto/constants.py
cryptoolzf/crypto/data.py
cryptoolzf/crypto/exceptions.py
cryptoolzf/crypto/algorithms/base.py
cryptoolzf/crypto/algorithms/shamir.py
cryptoolzf/resources/primes_least_pow_two.json
cryptoolzf-2.1.0.dist-info/AUTHORS.rst
cryptoolzf-2.1.0.dist-info/LICENSE
cryptoolzf-2.1.0.dist-info/METADATA
cryptoolzf-2.1.0.dist-info/WHEEL
cryptoolzf-2.1.0.dist-info/entry_points.txt
cryptoolzf-2.1.0.dist-info/top_level.txt
cryptoolzf-2.1.0.dist-info/RECORD
