Metadata-Version: 2.1
Name: cryptoolzf
Version: 2.1.0
Summary: A small high-level crypto library / cli toolset.
Home-page: https://github.org/mtugan/cryptoolzf
Author: Mtugan
Author-email: havanaguilahava@proton.me
License: GNU General Public License v3
Classifier: License :: OSI Approved :: GNU General Public License v3 (GPLv3)
Classifier: Development Status :: 3 - Alpha
Classifier: Programming Language :: Python :: 3.11
Classifier: Natural Language :: English
Classifier: Topic :: Software Development :: Version Control :: Git
License-File: LICENSE
License-File: AUTHORS.rst
Requires-Dist: asn1crypto ==1.5.1
Requires-Dist: cffi ==1.15.1
Requires-Dist: click ==8.1.3
Requires-Dist: pydantic <2
Requires-Dist: pydantic-core <2
Requires-Dist: cryptography ==39.0.0
Requires-Dist: cytoolz ==0.12.1
Requires-Dist: coincurve ==18.0.0
Requires-Dist: eth-utils ==2.1.0
Requires-Dist: eth-hash[pycryptodome] ==0.5.1
Requires-Dist: eth-typing ==3.2.0
Requires-Dist: pycparser ==2.21
Requires-Dist: segno ==1.5.2
Requires-Dist: pycryptodome ==3.16.0
Requires-Dist: typing-extensions ==4.4.0
Provides-Extra: dev
Requires-Dist: build[virtualenv] ; extra == 'dev'
Requires-Dist: bump2version ; extra == 'dev'
Requires-Dist: wheel ; extra == 'dev'
Requires-Dist: watchdog ; extra == 'dev'
Requires-Dist: flake8 ; extra == 'dev'
Requires-Dist: tox ; extra == 'dev'
Requires-Dist: coverage ; extra == 'dev'
Requires-Dist: Sphinx ; extra == 'dev'
Requires-Dist: twine ; extra == 'dev'
Requires-Dist: black ; extra == 'dev'
Requires-Dist: mypy ; extra == 'dev'
